running_sign/__init__.py
running_sign/running_sign.py
running_sign-0.1.3.dist-info/LICENSE
running_sign-0.1.3.dist-info/METADATA
running_sign-0.1.3.dist-info/WHEEL
running_sign-0.1.3.dist-info/top_level.txt
running_sign-0.1.3.dist-info/RECORD
