Metadata-Version: 2.1
Name: running-sign
Version: 0.1.3
Summary: progress indicator while program running
Home-page: https://github.com/jryzj/running_sign
Author: Jerry Zang
Author-email: 2381002887@qq.com
License: MIT
Keywords: progress,indicator,sign,program,running
Platform: UNKNOWN
Classifier: Intended Audience :: Developers
Classifier: License :: OSI Approved :: MIT License
Classifier: Programming Language :: Python :: 3
Classifier: Development Status :: 3 - Alpha
Requires-Python: >=3
Requires-Dist: apscheduler
